lumiere/__init__.py
lumiere/backend/__init__.py
lumiere/backend/activation_functions.py
lumiere/backend/explain/__init__.py
lumiere/backend/explain/pdp.py
lumiere/backend/explain/shapley.py
lumiere/backend/mlp.py
lumiere/backend/utils.py
lumiere/py.typed
lumiere/typing.py
bella_lumiere-0.0.14.dist-info/METADATA
bella_lumiere-0.0.14.dist-info/WHEEL
bella_lumiere-0.0.14.dist-info/RECORD
