Metadata-Version: 2.1
Name: bella-lumiere
Version: 0.0.14
Summary: Live Utilities for Model Inspection and Exploration of Relevant Effects
Author: gabriele-marino
Author-email: gabmarino.8601@gmail.com
Requires-Python: >=3.10,<4.0
Classifier: Programming Language :: Python :: 3
Classifier: Programming Language :: Python :: 3.10
Classifier: Programming Language :: Python :: 3.11
Classifier: Programming Language :: Python :: 3.12
Requires-Dist: polars (>=1.32.3,<2.0.0)
Requires-Dist: shap (>=0.48.0,<0.49.0)
